.ignore
COPYING
buildInstall
setup.py
doc/Makefile
doc/createRsts.py
doc/build/.ignore
doc/source/changelog.rst
doc/source/conf.py
doc/source/config.rst
doc/source/index.rst
doc/source/installation.rst
doc/source/intro.rst
doc/source/logging.rst
doc/source/networking.rst
doc/source/patterns.rst
doc/source/processes.rst
doc/source/system.rst
doc/source/ui.rst
doc/source/util.rst
doc/source/web.rst
doc/source/_generated/.ignore
files/admin.txt
pyamp/__init__.py
pyamp/exceptions.py
pyamp.egg-info/PKG-INFO
pyamp.egg-info/SOURCES.txt
pyamp.egg-info/dependency_links.txt
pyamp.egg-info/top_level.txt
pyamp/config/__init__.py
pyamp/config/configFile.py
pyamp/config/conversions.py
pyamp/config/option.py
pyamp/config/parser.py
pyamp/documentation/__init__.py
pyamp/documentation/rstGeneration.py
pyamp/logging/__init__.py
pyamp/logging/colors.py
pyamp/logging/loggable.py
pyamp/logging/logger.py
pyamp/logging/meta.py
pyamp/logging/prefix.py
pyamp/networking/__init__.py
pyamp/networking/sockets/__init__.py
pyamp/networking/sockets/connection.py
pyamp/networking/sockets/server.py
pyamp/patterns/__init__.py
pyamp/patterns/borg.py
pyamp/patterns/decorators.py
pyamp/patterns/enum.py
pyamp/patterns/interfaces/__init__.py
pyamp/patterns/interfaces/finalFunctionsMeta.py
pyamp/patterns/interfaces/interface.py
pyamp/patterns/interfaces/requiredProperties.py
pyamp/processes/__init__.py
pyamp/processes/coroutine.py
pyamp/processes/threading/__init__.py
pyamp/processes/threading/thread.py
pyamp/system/__init__.py
pyamp/system/ubuntu/__init__.py
pyamp/system/ubuntu/menu.py
pyamp/system/ubuntu/packages.py
pyamp/ui/__init__.py
pyamp/ui/input/__init__.py
pyamp/ui/input/console.py
pyamp/ui/input/evdev.py
pyamp/ui/input/keys.py
pyamp/ui/input/userInput.py
pyamp/ui/qt/__init__.py
pyamp/ui/qt/baseView.py
pyamp/ui/qt/baseWidget.py
pyamp/ui/qt/interrupt.py
pyamp/ui/qt/keyEvents.py
pyamp/ui/qt/resizePolicy.py
pyamp/ui/qt/scrollableList.py
pyamp/ui/qt/spacers.py
pyamp/ui/qt/styleSheet.py
pyamp/ui/qt/widgetList.py
pyamp/util/__init__.py
pyamp/util/debugging.py
pyamp/util/dictionary.py
pyamp/util/directories.py
