Metadata-Version: 1.0
Name: pyamp
Version: 1.2
Summary: pyamp module for Python
Home-page: https://code.google.com/p/pyamp/
Author: Brett Ponsler
Author-email: ponsler@gmail.com
License: GNU GPL v3
Platform: UNKNOWN
